{
  "project_info": {
    "project_number": "204772927129",
    "project_id": "userdata-f7f58",
    "storage_bucket": "userdata-f7f58.appspot.com"
  },
  "client": [
    {
      "client_info": {
        "mobilesdk_app_id": "1:204772927129:android:8c7ead832ca9c5e5537a08",
        "android_client_info": {
          "package_name": "com.example.userdataapplication"
        }
      },
      "oauth_client": [
        {
          "client_id": "204772927129-rlr8p46lgbur5upa5k79n20t5c3qgc45.apps.googleusercontent.com",
          "client_type": 3
        }
      ],
      "api_key": [
        {
          "current_key": "AIzaSyAf3dc2Gs7P0rVEfuJJ_SS67ndNIy0FrPg"
        }
      ],
      "services": {
        "appinvite_service": {
          "other_platform_oauth_client": [
            {
              "client_id": "204772927129-rlr8p46lgbur5upa5k79n20t5c3qgc45.apps.googleusercontent.com",
              "client_type": 3
            }
          ]
        }
      }
    }
  ],
  "configuration_version": "1"
}